MANIFEST.in
README.rst
setup.py
aliyun_python_sdk_dnsknocker.egg-info/PKG-INFO
aliyun_python_sdk_dnsknocker.egg-info/SOURCES.txt
aliyun_python_sdk_dnsknocker.egg-info/dependency_links.txt
aliyun_python_sdk_dnsknocker.egg-info/requires.txt
aliyun_python_sdk_dnsknocker.egg-info/top_level.txt
aliyunsdkdnsknocker/__init__.py
aliyunsdkdnsknocker/endpoint.py
aliyunsdkdnsknocker/request/__init__.py
aliyunsdkdnsknocker/request/v20190910/BatchCreateRrRequest.py
aliyunsdkdnsknocker/request/v20190910/BatchDeleteRrRequest.py
aliyunsdkdnsknocker/request/v20190910/ChangeResourceRecordRequest.py
aliyunsdkdnsknocker/request/v20190910/ChangeResourceRecordsRequest.py
aliyunsdkdnsknocker/request/v20190910/CreateResourceRecordRequest.py
aliyunsdkdnsknocker/request/v20190910/DeleteDomainRequest.py
aliyunsdkdnsknocker/request/v20190910/DeleteResourceRecordRequest.py
aliyunsdkdnsknocker/request/v20190910/DeleteResourceRecordsRequest.py
aliyunsdkdnsknocker/request/v20190910/GetDomainRequest.py
aliyunsdkdnsknocker/request/v20190910/GetResourceRecordsRequest.py
aliyunsdkdnsknocker/request/v20190910/__init__.py